kinematicsolver/__init__.py
kinematicsolver/kinematicsolvermethods.py
kinematicsolver-1.5.0.dist-info/licenses/LICENSE
kinematicsolver-1.5.0.dist-info/METADATA
kinematicsolver-1.5.0.dist-info/WHEEL
kinematicsolver-1.5.0.dist-info/top_level.txt
kinematicsolver-1.5.0.dist-info/RECORD
